{
  "firstLayout": "",
  "gdVersion": {
    "build": 217,
    "major": 5,
    "minor": 4,
    "revision": 0
  },
  "properties": {
    "adaptGameResolutionAtRuntime": true,
    "antialiasingMode": "MSAA",
    "antialisingEnabledOnMobile": false,
    "folderProject": true,
    "orientation": "default",
    "packageName": "com.example.gamename",
    "pixelsRounding": true,
    "projectUuid": "90843a45-0ca5-4dcd-b538-a7e6e946517f",
    "scaleMode": "nearest",
    "sizeOnStartupMode": "adaptWidth",
    "templateSlug": "",
    "useExternalSourceFiles": false,
    "version": "1.0.0",
    "name": "80k rpg",
    "description": "",
    "author": "",
    "windowWidth": 800,
    "windowHeight": 600,
    "latestCompilationDirectory": "",
    "maxFPS": 60,
    "minFPS": 20,
    "verticalSync": false,
    "platformSpecificAssets": {},
    "loadingScreen": {
      "backgroundColor": 0,
      "backgroundFadeInDuration": 0.2,
      "backgroundImageResourceName": "",
      "gdevelopLogoStyle": "light",
      "logoAndProgressFadeInDuration": 0.2,
      "logoAndProgressLogoFadeInDelay": 0,
      "minDuration": 1.5,
      "progressBarColor": 16777215,
      "progressBarHeight": 20,
      "progressBarMaxWidth": 200,
      "progressBarMinWidth": 40,
      "progressBarWidthPercent": 30,
      "showGDevelopSplash": true,
      "showProgressBar": true
    },
    "watermark": {
      "placement": "bottom-left",
      "showWatermark": true
    },
    "authorIds": [],
    "authorUsernames": [],
    "categories": [],
    "playableDevices": [],
    "extensionProperties": [],
    "platforms": [
      {
        "name": "GDevelop JS platform"
      }
    ],
    "currentPlatform": "GDevelop JS platform"
  },
  "resources": {
    "resources": [
      {
        "alwaysLoaded": false,
        "file": "assets/mapPack_tilesheet_2X.png",
        "kind": "image",
        "metadata": "",
        "name": "mapPack_tilesheet_2X.png",
        "smoothed": false,
        "userAdded": true,
        "origin": {
          "identifier": "https://asset-resources.gdevelop.io/public-resources/Kenney Tilemaps/High Definition/5f0063211bf3fddcc0a7c68a2cafb734e57e96df0f5a55d4906ffcfac71936b0_mapPack_tilesheet_2X.png",
          "name": "mapPack_tilesheet_2X.png"
        }
      },
      {
        "alwaysLoaded": false,
        "file": "../../Users/kayng/Downloads/RF_Catacombs_v1.0/mainlevbuild.png",
        "kind": "image",
        "metadata": "",
        "name": "..\\..\\Users\\kayng\\Downloads\\RF_Catacombs_v1.0\\mainlevbuild.png",
        "smoothed": false,
        "userAdded": false
      },
      {
        "alwaysLoaded": false,
        "file": "mainlevbuild.png",
        "kind": "image",
        "metadata": "",
        "name": "mainlevbuild.png",
        "smoothed": false,
        "userAdded": false
      },
      {
        "alwaysLoaded": false,
        "file": "Skeleton.png",
        "kind": "image",
        "metadata": "",
        "name": "Skeleton.png",
        "smoothed": false,
        "userAdded": false
      },
      {
        "alwaysLoaded": false,
        "file": "assets/Skeleton.png",
        "kind": "image",
        "metadata": "{\"extension\":\".png\",\"localFilePath\":\"assets/Skeleton.png\"}",
        "name": "Skeleton",
        "smoothed": false,
        "userAdded": false
      },
      {
        "alwaysLoaded": false,
        "file": "assets/Skeleton2.png",
        "kind": "image",
        "metadata": "{\"extension\":\".png\",\"localFilePath\":\"assets/Skeleton2.png\"}",
        "name": "Skeleton2",
        "smoothed": false,
        "userAdded": false
      },
      {
        "alwaysLoaded": false,
        "file": "assets/Skeleton3.png",
        "kind": "image",
        "metadata": "{\"extension\":\".png\",\"localFilePath\":\"assets/Skeleton3.png\"}",
        "name": "Skeleton3",
        "smoothed": false,
        "userAdded": false
      },
      {
        "alwaysLoaded": false,
        "file": "assets/Skeleton4.png",
        "kind": "image",
        "metadata": "{\"extension\":\".png\",\"localFilePath\":\"assets/Skeleton4.png\"}",
        "name": "Skeleton4",
        "smoothed": false,
        "userAdded": false
      },
      {
        "alwaysLoaded": false,
        "file": "assets/Skeleton5.png",
        "kind": "image",
        "metadata": "{\"extension\":\".png\"}",
        "name": "Skeleton5",
        "smoothed": false,
        "userAdded": false
      },
      {
        "alwaysLoaded": false,
        "file": "assets/Skeleton6.png",
        "kind": "image",
        "metadata": "{\"extension\":\".png\"}",
        "name": "Skeleton6",
        "smoothed": false,
        "userAdded": false
      },
      {
        "alwaysLoaded": false,
        "file": "assets/Skeleton7.png",
        "kind": "image",
        "metadata": "{\"extension\":\".png\"}",
        "name": "Skeleton7",
        "smoothed": false,
        "userAdded": false
      },
      {
        "alwaysLoaded": false,
        "file": "assets/Skeleton8.png",
        "kind": "image",
        "metadata": "{\"extension\":\".png\"}",
        "name": "Skeleton8",
        "smoothed": false,
        "userAdded": false
      },
      {
        "alwaysLoaded": false,
        "file": "assets/Skeleton9.png",
        "kind": "image",
        "metadata": "{\"extension\":\".png\"}",
        "name": "Skeleton9",
        "smoothed": false,
        "userAdded": false
      },
      {
        "alwaysLoaded": false,
        "file": "assets/Skeleton10.png",
        "kind": "image",
        "metadata": "{\"extension\":\".png\"}",
        "name": "Skeleton10",
        "smoothed": false,
        "userAdded": false
      },
      {
        "alwaysLoaded": false,
        "file": "assets/Skeleton11.png",
        "kind": "image",
        "metadata": "{\"extension\":\".png\"}",
        "name": "Skeleton11",
        "smoothed": false,
        "userAdded": false
      },
      {
        "alwaysLoaded": false,
        "file": "assets/Skeleton12.png",
        "kind": "image",
        "metadata": "{\"extension\":\".png\"}",
        "name": "Skeleton12",
        "smoothed": false,
        "userAdded": false
      },
      {
        "alwaysLoaded": false,
        "file": "assets/Skeleton13.png",
        "kind": "image",
        "metadata": "{\"extension\":\".png\"}",
        "name": "Skeleton13",
        "smoothed": false,
        "userAdded": false
      },
      {
        "alwaysLoaded": false,
        "file": "assets/Skeleton14.png",
        "kind": "image",
        "metadata": "{\"extension\":\".png\"}",
        "name": "Skeleton14",
        "smoothed": false,
        "userAdded": false
      },
      {
        "alwaysLoaded": false,
        "file": "assets/Skeleton15.png",
        "kind": "image",
        "metadata": "{\"extension\":\".png\"}",
        "name": "Skeleton15",
        "smoothed": false,
        "userAdded": false
      },
      {
        "alwaysLoaded": false,
        "file": "assets/Skeleton16.png",
        "kind": "image",
        "metadata": "{\"extension\":\".png\"}",
        "name": "Skeleton16",
        "smoothed": false,
        "userAdded": false
      },
      {
        "alwaysLoaded": false,
        "file": "assets/Skeleton17.png",
        "kind": "image",
        "metadata": "{\"extension\":\".png\"}",
        "name": "Skeleton17",
        "smoothed": false,
        "userAdded": false
      },
      {
        "alwaysLoaded": false,
        "file": "assets/Skeleton18.png",
        "kind": "image",
        "metadata": "{\"extension\":\".png\"}",
        "name": "Skeleton18",
        "smoothed": false,
        "userAdded": false
      },
      {
        "alwaysLoaded": false,
        "file": "assets/Skeleton19.png",
        "kind": "image",
        "metadata": "{\"extension\":\".png\"}",
        "name": "Skeleton19",
        "smoothed": false,
        "userAdded": false
      },
      {
        "alwaysLoaded": false,
        "file": "assets/Skeleton20.png",
        "kind": "image",
        "metadata": "{\"extension\":\".png\"}",
        "name": "Skeleton20",
        "smoothed": false,
        "userAdded": false
      },
      {
        "alwaysLoaded": false,
        "file": "assets/Skeleton21.png",
        "kind": "image",
        "metadata": "{\"extension\":\".png\"}",
        "name": "Skeleton21",
        "smoothed": false,
        "userAdded": false
      },
      {
        "alwaysLoaded": false,
        "file": "assets/Skeleton22.png",
        "kind": "image",
        "metadata": "{\"extension\":\".png\"}",
        "name": "Skeleton22",
        "smoothed": false,
        "userAdded": false
      },
      {
        "alwaysLoaded": false,
        "file": "assets/Skeleton23.png",
        "kind": "image",
        "metadata": "{\"extension\":\".png\"}",
        "name": "Skeleton23",
        "smoothed": false,
        "userAdded": false
      },
      {
        "alwaysLoaded": false,
        "file": "assets/Skeleton24.png",
        "kind": "image",
        "metadata": "{\"extension\":\".png\"}",
        "name": "Skeleton24",
        "smoothed": false,
        "userAdded": false
      },
      {
        "alwaysLoaded": false,
        "file": "assets/Skeleton25.png",
        "kind": "image",
        "metadata": "{\"extension\":\".png\"}",
        "name": "Skeleton25",
        "smoothed": false,
        "userAdded": false
      },
      {
        "alwaysLoaded": false,
        "file": "assets/Skeleton26.png",
        "kind": "image",
        "metadata": "{\"extension\":\".png\"}",
        "name": "Skeleton26",
        "smoothed": false,
        "userAdded": false
      },
      {
        "alwaysLoaded": false,
        "file": "assets/Skeleton27.png",
        "kind": "image",
        "metadata": "{\"extension\":\".png\"}",
        "name": "Skeleton27",
        "smoothed": false,
        "userAdded": false
      },
      {
        "alwaysLoaded": false,
        "file": "assets/Skeleton28.png",
        "kind": "image",
        "metadata": "{\"extension\":\".png\"}",
        "name": "Skeleton28",
        "smoothed": false,
        "userAdded": false
      },
      {
        "alwaysLoaded": false,
        "file": "assets/Skeleton29.png",
        "kind": "image",
        "metadata": "{\"extension\":\".png\"}",
        "name": "Skeleton29",
        "smoothed": false,
        "userAdded": false
      },
      {
        "alwaysLoaded": false,
        "file": "assets/Skeleton30.png",
        "kind": "image",
        "metadata": "{\"extension\":\".png\"}",
        "name": "Skeleton30",
        "smoothed": false,
        "userAdded": false
      },
      {
        "alwaysLoaded": false,
        "file": "assets/Skeleton31.png",
        "kind": "image",
        "metadata": "{\"extension\":\".png\"}",
        "name": "Skeleton31",
        "smoothed": false,
        "userAdded": false
      },
      {
        "alwaysLoaded": false,
        "file": "assets/Skeleton32.png",
        "kind": "image",
        "metadata": "{\"extension\":\".png\"}",
        "name": "Skeleton32",
        "smoothed": false,
        "userAdded": false
      },
      {
        "alwaysLoaded": false,
        "file": "assets/Skeleton33.png",
        "kind": "image",
        "metadata": "{\"extension\":\".png\"}",
        "name": "Skeleton33",
        "smoothed": false,
        "userAdded": false
      },
      {
        "alwaysLoaded": false,
        "file": "assets/Skeleton34.png",
        "kind": "image",
        "metadata": "{\"extension\":\".png\"}",
        "name": "Skeleton34",
        "smoothed": false,
        "userAdded": false
      },
      {
        "alwaysLoaded": false,
        "file": "assets/Skeleton35.png",
        "kind": "image",
        "metadata": "{\"extension\":\".png\"}",
        "name": "Skeleton35",
        "smoothed": false,
        "userAdded": false
      },
      {
        "alwaysLoaded": false,
        "file": "assets/Skeleton36.png",
        "kind": "image",
        "metadata": "{\"extension\":\".png\"}",
        "name": "Skeleton36",
        "smoothed": false,
        "userAdded": false
      },
      {
        "alwaysLoaded": false,
        "file": "assets/Skeleton37.png",
        "kind": "image",
        "metadata": "{\"extension\":\".png\"}",
        "name": "Skeleton37",
        "smoothed": false,
        "userAdded": false
      },
      {
        "alwaysLoaded": false,
        "file": "assets/Skeleton38.png",
        "kind": "image",
        "metadata": "{\"extension\":\".png\"}",
        "name": "Skeleton38",
        "smoothed": false,
        "userAdded": false
      },
      {
        "alwaysLoaded": false,
        "file": "assets/Skeleton39.png",
        "kind": "image",
        "metadata": "{\"extension\":\".png\"}",
        "name": "Skeleton39",
        "smoothed": false,
        "userAdded": false
      },
      {
        "alwaysLoaded": false,
        "file": "assets/Skeleton40.png",
        "kind": "image",
        "metadata": "{\"extension\":\".png\"}",
        "name": "Skeleton40",
        "smoothed": false,
        "userAdded": false
      },
      {
        "alwaysLoaded": false,
        "file": "assets/Skeleton41.png",
        "kind": "image",
        "metadata": "{\"extension\":\".png\"}",
        "name": "Skeleton41",
        "smoothed": false,
        "userAdded": false
      },
      {
        "alwaysLoaded": false,
        "file": "assets/Skeleton42.png",
        "kind": "image",
        "metadata": "{\"extension\":\".png\"}",
        "name": "Skeleton42",
        "smoothed": false,
        "userAdded": false
      },
      {
        "alwaysLoaded": false,
        "file": "assets/Dino Mort_Crouch.png",
        "kind": "image",
        "metadata": "",
        "name": "Dino Mort_Crouch.png",
        "smoothed": false,
        "userAdded": false,
        "origin": {
          "identifier": "https://asset-resources.gdevelop.io/public-resources/24x24 Dino Characters/9c1851f6928ea3038f327ebc4979c0665f8deec54f36321529802d81fcabef99_Dino Mort_Crouch.png",
          "name": "Dino Mort_Crouch.png"
        }
      },
      {
        "alwaysLoaded": false,
        "file": "assets/Dino Mort_Hurt_1.png",
        "kind": "image",
        "metadata": "",
        "name": "Dino Mort_Hurt_1.png",
        "smoothed": false,
        "userAdded": false,
        "origin": {
          "identifier": "https://asset-resources.gdevelop.io/public-resources/24x24 Dino Characters/817711599b5b70130ff0994d4329c757d9894e5cb4d406189cd928208d188e13_Dino Mort_Hurt_1.png",
          "name": "Dino Mort_Hurt_1.png"
        }
      },
      {
        "alwaysLoaded": false,
        "file": "assets/Dino Mort_Hurt_2.png",
        "kind": "image",
        "metadata": "",
        "name": "Dino Mort_Hurt_2.png",
        "smoothed": false,
        "userAdded": false,
        "origin": {
          "identifier": "https://asset-resources.gdevelop.io/public-resources/24x24 Dino Characters/6d1ed60b9aa070dea0ba241ffb08d7f64f5c7feac8afe72bb52a73fe12dbbb9d_Dino Mort_Hurt_2.png",
          "name": "Dino Mort_Hurt_2.png"
        }
      },
      {
        "alwaysLoaded": false,
        "file": "assets/Dino Mort_Hurt_3.png",
        "kind": "image",
        "metadata": "",
        "name": "Dino Mort_Hurt_3.png",
        "smoothed": false,
        "userAdded": false,
        "origin": {
          "identifier": "https://asset-resources.gdevelop.io/public-resources/24x24 Dino Characters/376ec93f22135845a7321bfef20d75d7d9fb9c37af4601edcae556814d748231_Dino Mort_Hurt_3.png",
          "name": "Dino Mort_Hurt_3.png"
        }
      },
      {
        "alwaysLoaded": false,
        "file": "assets/Dino Mort_Hurt_4.png",
        "kind": "image",
        "metadata": "",
        "name": "Dino Mort_Hurt_4.png",
        "smoothed": false,
        "userAdded": false,
        "origin": {
          "identifier": "https://asset-resources.gdevelop.io/public-resources/24x24 Dino Characters/b8755556d5dfff50ad2eeacd4ed24c1cbcd044a5e2baf60a5354cd7072c1dbc3_Dino Mort_Hurt_4.png",
          "name": "Dino Mort_Hurt_4.png"
        }
      },
      {
        "alwaysLoaded": false,
        "file": "assets/Dino Mort_Idle_1.png",
        "kind": "image",
        "metadata": "",
        "name": "Dino Mort_Idle_1.png",
        "smoothed": false,
        "userAdded": false,
        "origin": {
          "identifier": "https://asset-resources.gdevelop.io/public-resources/24x24 Dino Characters/817711599b5b70130ff0994d4329c757d9894e5cb4d406189cd928208d188e13_Dino Mort_Idle_1.png",
          "name": "Dino Mort_Idle_1.png"
        }
      },
      {
        "alwaysLoaded": false,
        "file": "assets/Dino Mort_Idle_2.png",
        "kind": "image",
        "metadata": "",
        "name": "Dino Mort_Idle_2.png",
        "smoothed": false,
        "userAdded": false,
        "origin": {
          "identifier": "https://asset-resources.gdevelop.io/public-resources/24x24 Dino Characters/fc8ae8e28bebf98703bb6ff546a7db32bb50d3d0518f1c6bf0a68287ff58ddb2_Dino Mort_Idle_2.png",
          "name": "Dino Mort_Idle_2.png"
        }
      },
      {
        "alwaysLoaded": false,
        "file": "assets/Dino Mort_Idle_3.png",
        "kind": "image",
        "metadata": "",
        "name": "Dino Mort_Idle_3.png",
        "smoothed": false,
        "userAdded": false,
        "origin": {
          "identifier": "https://asset-resources.gdevelop.io/public-resources/24x24 Dino Characters/d77f1995f3f9fca42cd4a7a3bad137f709886cb65f17126fd259642db0bdac7c_Dino Mort_Idle_3.png",
          "name": "Dino Mort_Idle_3.png"
        }
      },
      {
        "alwaysLoaded": false,
        "file": "assets/Dino Mort_Idle_4.png",
        "kind": "image",
        "metadata": "",
        "name": "Dino Mort_Idle_4.png",
        "smoothed": false,
        "userAdded": false,
        "origin": {
          "identifier": "https://asset-resources.gdevelop.io/public-resources/24x24 Dino Characters/817711599b5b70130ff0994d4329c757d9894e5cb4d406189cd928208d188e13_Dino Mort_Idle_4.png",
          "name": "Dino Mort_Idle_4.png"
        }
      },
      {
        "alwaysLoaded": false,
        "file": "assets/Dino Mort_Kick_1.png",
        "kind": "image",
        "metadata": "",
        "name": "Dino Mort_Kick_1.png",
        "smoothed": false,
        "userAdded": false,
        "origin": {
          "identifier": "https://asset-resources.gdevelop.io/public-resources/24x24 Dino Characters/817711599b5b70130ff0994d4329c757d9894e5cb4d406189cd928208d188e13_Dino Mort_Kick_1.png",
          "name": "Dino Mort_Kick_1.png"
        }
      },
      {
        "alwaysLoaded": false,
        "file": "assets/Dino Mort_Kick_2.png",
        "kind": "image",
        "metadata": "",
        "name": "Dino Mort_Kick_2.png",
        "smoothed": false,
        "userAdded": false,
        "origin": {
          "identifier": "https://asset-resources.gdevelop.io/public-resources/24x24 Dino Characters/1ad830a82cd7ce4e32055f44b9804c337a0358830d60e03d92010024fe484519_Dino Mort_Kick_2.png",
          "name": "Dino Mort_Kick_2.png"
        }
      },
      {
        "alwaysLoaded": false,
        "file": "assets/Dino Mort_Kick_3.png",
        "kind": "image",
        "metadata": "",
        "name": "Dino Mort_Kick_3.png",
        "smoothed": false,
        "userAdded": false,
        "origin": {
          "identifier": "https://asset-resources.gdevelop.io/public-resources/24x24 Dino Characters/2fc01d656b8f5a382f7ce4ec5b12c45facc8a8d55f03eeee3cf0b556d3c5d2e7_Dino Mort_Kick_3.png",
          "name": "Dino Mort_Kick_3.png"
        }
      },
      {
        "alwaysLoaded": false,
        "file": "assets/Dino Mort_Move_1.png",
        "kind": "image",
        "metadata": "",
        "name": "Dino Mort_Move_1.png",
        "smoothed": false,
        "userAdded": false,
        "origin": {
          "identifier": "https://asset-resources.gdevelop.io/public-resources/24x24 Dino Characters/89275a322de93f3973b801d47da481a261d3a505d9039cb090a6d93f7bc76c53_Dino Mort_Move_1.png",
          "name": "Dino Mort_Move_1.png"
        }
      },
      {
        "alwaysLoaded": false,
        "file": "assets/Dino Mort_Move_2.png",
        "kind": "image",
        "metadata": "",
        "name": "Dino Mort_Move_2.png",
        "smoothed": false,
        "userAdded": false,
        "origin": {
          "identifier": "https://asset-resources.gdevelop.io/public-resources/24x24 Dino Characters/1e64115026383fc1654f9f0fa7f339e71d51bcd099f7336013708f594496347b_Dino Mort_Move_2.png",
          "name": "Dino Mort_Move_2.png"
        }
      },
      {
        "alwaysLoaded": false,
        "file": "assets/Dino Mort_Move_3.png",
        "kind": "image",
        "metadata": "",
        "name": "Dino Mort_Move_3.png",
        "smoothed": false,
        "userAdded": false,
        "origin": {
          "identifier": "https://asset-resources.gdevelop.io/public-resources/24x24 Dino Characters/c5482d5f5e51e978b91b8edbc9343c0d7e8f99598c60df49720f88d8227c347a_Dino Mort_Move_3.png",
          "name": "Dino Mort_Move_3.png"
        }
      },
      {
        "alwaysLoaded": false,
        "file": "assets/Dino Mort_Move_4.png",
        "kind": "image",
        "metadata": "",
        "name": "Dino Mort_Move_4.png",
        "smoothed": false,
        "userAdded": false,
        "origin": {
          "identifier": "https://asset-resources.gdevelop.io/public-resources/24x24 Dino Characters/28fce1ffcc31e85d2b79a6c2534aea05903c90a6c321f74c2d2f7d44e82e7f89_Dino Mort_Move_4.png",
          "name": "Dino Mort_Move_4.png"
        }
      },
      {
        "alwaysLoaded": false,
        "file": "assets/Dino Mort_Move_5.png",
        "kind": "image",
        "metadata": "",
        "name": "Dino Mort_Move_5.png",
        "smoothed": false,
        "userAdded": false,
        "origin": {
          "identifier": "https://asset-resources.gdevelop.io/public-resources/24x24 Dino Characters/621858554348527ab61d9fbfaae18e38642d47fe752afc052ffb35fab3421b6e_Dino Mort_Move_5.png",
          "name": "Dino Mort_Move_5.png"
        }
      },
      {
        "alwaysLoaded": false,
        "file": "assets/Dino Mort_Move_6.png",
        "kind": "image",
        "metadata": "",
        "name": "Dino Mort_Move_6.png",
        "smoothed": false,
        "userAdded": false,
        "origin": {
          "identifier": "https://asset-resources.gdevelop.io/public-resources/24x24 Dino Characters/5a127c5493da78ce1c7678244bdf3c529f7b4b4bbc8f477f271f7fc72b104eab_Dino Mort_Move_6.png",
          "name": "Dino Mort_Move_6.png"
        }
      },
      {
        "alwaysLoaded": false,
        "file": "assets/Dino Mort_Sneak_1.png",
        "kind": "image",
        "metadata": "",
        "name": "Dino Mort_Sneak_1.png",
        "smoothed": false,
        "userAdded": false,
        "origin": {
          "identifier": "https://asset-resources.gdevelop.io/public-resources/24x24 Dino Characters/68ddb42eeaec0fbe16331a078bfff367a3acd0bd5ea3ad492f1960f6e3c90d3d_Dino Mort_Sneak_1.png",
          "name": "Dino Mort_Sneak_1.png"
        }
      },
      {
        "alwaysLoaded": false,
        "file": "assets/Dino Mort_Sneak_2.png",
        "kind": "image",
        "metadata": "",
        "name": "Dino Mort_Sneak_2.png",
        "smoothed": false,
        "userAdded": false,
        "origin": {
          "identifier": "https://asset-resources.gdevelop.io/public-resources/24x24 Dino Characters/e6ee94464b6897e28cd862d8ab3644d6d0ad43f117ba04ddf4be616db77aec54_Dino Mort_Sneak_2.png",
          "name": "Dino Mort_Sneak_2.png"
        }
      },
      {
        "alwaysLoaded": false,
        "file": "assets/Dino Mort_Sneak_3.png",
        "kind": "image",
        "metadata": "",
        "name": "Dino Mort_Sneak_3.png",
        "smoothed": false,
        "userAdded": false,
        "origin": {
          "identifier": "https://asset-resources.gdevelop.io/public-resources/24x24 Dino Characters/62cf6c0321a69b2d00c386e4cfbbe28c37a636f5aae2b81cdc1c856b78032268_Dino Mort_Sneak_3.png",
          "name": "Dino Mort_Sneak_3.png"
        }
      },
      {
        "alwaysLoaded": false,
        "file": "assets/Dino Mort_Sneak_4.png",
        "kind": "image",
        "metadata": "",
        "name": "Dino Mort_Sneak_4.png",
        "smoothed": false,
        "userAdded": false,
        "origin": {
          "identifier": "https://asset-resources.gdevelop.io/public-resources/24x24 Dino Characters/a591ffc8eef885911814c5f644bcbbd820f319a322fb522c4dbc7d7e83c506a2_Dino Mort_Sneak_4.png",
          "name": "Dino Mort_Sneak_4.png"
        }
      },
      {
        "alwaysLoaded": false,
        "file": "assets/Dino Mort_Sneak_5.png",
        "kind": "image",
        "metadata": "",
        "name": "Dino Mort_Sneak_5.png",
        "smoothed": false,
        "userAdded": false,
        "origin": {
          "identifier": "https://asset-resources.gdevelop.io/public-resources/24x24 Dino Characters/4be90b3305e09b32737ad4544ea458d8fb251a8b092964a972e18f28b8059555_Dino Mort_Sneak_5.png",
          "name": "Dino Mort_Sneak_5.png"
        }
      },
      {
        "alwaysLoaded": false,
        "file": "assets/Dino Mort_Sneak_6.png",
        "kind": "image",
        "metadata": "",
        "name": "Dino Mort_Sneak_6.png",
        "smoothed": false,
        "userAdded": false,
        "origin": {
          "identifier": "https://asset-resources.gdevelop.io/public-resources/24x24 Dino Characters/1c4882da78d02e0e0a5fc64979d93d70f1800c734c6efa52a0316e80819fea7c_Dino Mort_Sneak_6.png",
          "name": "Dino Mort_Sneak_6.png"
        }
      },
      {
        "alwaysLoaded": false,
        "file": "assets/Wall.png",
        "kind": "image",
        "metadata": "{\"extension\":\".png\",\"pskl\":{},\"localFilePath\":\"assets/Wall.png\"}",
        "name": "Wall",
        "smoothed": false,
        "userAdded": false
      },
      {
        "alwaysLoaded": false,
        "file": "assets/Wall Red Flat.png",
        "kind": "image",
        "metadata": "",
        "name": "Wall Red Flat.png",
        "smoothed": false,
        "userAdded": false,
        "origin": {
          "identifier": "https://asset-resources.gdevelop.io/public-resources/Kenney Sokoban/Wall/80d468c94d67ff96222d16e34d5e70f7ac485746862a7308242786d40a8f7ca5_Wall Red Flat.png",
          "name": "Wall Red Flat.png"
        }
      },
      {
        "alwaysLoaded": false,
        "file": "assets/Bronze Sword.png",
        "kind": "image",
        "metadata": "{\"localFilePath\":\"assets/Bronze Sword.png\",\"extension\":\".png\"}",
        "name": "Bronze Sword.png",
        "smoothed": false,
        "userAdded": false,
        "origin": {
          "identifier": "https://asset-resources.gdevelop.io/public-resources/16x16 Pixel art RPG Items/Weapons/20de09f91cf2cb8bc411d9ed9bcea9c91ec051ab8519cf8dc5f00cd839c18a65_Bronze Sword.png",
          "name": "Bronze Sword.png"
        }
      },
      {
        "alwaysLoaded": false,
        "file": "assets/Bronze Sword2.png",
        "kind": "image",
        "metadata": "{\"extension\":\".png\"}",
        "name": "Bronze Sword",
        "smoothed": false,
        "userAdded": false
      },
      {
        "alwaysLoaded": false,
        "file": "assets/Monster.png",
        "kind": "image",
        "metadata": "",
        "name": "Monster.png",
        "smoothed": false,
        "userAdded": false,
        "origin": {
          "identifier": "https://asset-resources.gdevelop.io/public-resources/Wesxdz Game Assets/skullcup/Characters/efcc4c7bd5d61af14041ce090f9facb0991e5fe42471ed980a92fd8322d97cc0_Monster.png",
          "name": "Monster.png"
        }
      },
      {
        "alwaysLoaded": false,
        "file": "assets/Projectile 3.png",
        "kind": "image",
        "metadata": "",
        "name": "Projectile 3.png",
        "smoothed": false,
        "userAdded": false,
        "origin": {
          "identifier": "https://asset-resources.gdevelop.io/public-resources/Wesxdz Game Assets/skullcup/Props/0b78fdd188255380ef39694b3ef392887670d8ca1a6c2893bec70fedf78037d2_Projectile 3.png",
          "name": "Projectile 3.png"
        }
      },
      {
        "alwaysLoaded": false,
        "file": "assets/Dot Bar Green Border.png",
        "kind": "image",
        "metadata": "",
        "name": "Dot Bar Green Border.png",
        "smoothed": false,
        "userAdded": false,
        "origin": {
          "identifier": "https://asset-resources.gdevelop.io/public-resources/Resource bars/pixel art/e0754c6008a7f3ec35ce32d663263982cd7a67f91974977d1c1247b90891b1b9_Dot Bar Green Border.png",
          "name": "Dot Bar Green Border.png"
        }
      },
      {
        "alwaysLoaded": false,
        "file": "assets/Dot Bar Green Fill Bar.png",
        "kind": "image",
        "metadata": "",
        "name": "Dot Bar Green Fill Bar.png",
        "smoothed": false,
        "userAdded": false,
        "origin": {
          "identifier": "https://asset-resources.gdevelop.io/public-resources/Resource bars/pixel art/11956f33bb9a6ca4997feced357ff80d8b2597367951d4ab34cd67d5a2d8b054_Dot Bar Green Fill Bar.png",
          "name": "Dot Bar Green Fill Bar.png"
        }
      },
      {
        "alwaysLoaded": false,
        "file": "assets/NewSprite.png",
        "kind": "image",
        "metadata": "{\"extension\":\".png\"}",
        "name": "NewSprite",
        "smoothed": false,
        "userAdded": false
      },
      {
        "alwaysLoaded": false,
        "file": "assets/NewSprite2.png",
        "kind": "image",
        "metadata": "{\"extension\":\".png\"}",
        "name": "NewSprite2",
        "smoothed": false,
        "userAdded": false
      },
      {
        "alwaysLoaded": false,
        "file": "assets/Health.png",
        "kind": "image",
        "metadata": "{\"extension\":\".png\",\"localFilePath\":\"assets/Health.png\"}",
        "name": "Health",
        "smoothed": false,
        "userAdded": false
      },
      {
        "alwaysLoaded": false,
        "file": "assets/Armor_Bar.png",
        "kind": "image",
        "metadata": "{\"extension\":\".png\"}",
        "name": "Armor_Bar",
        "smoothed": false,
        "userAdded": false
      },
      {
        "alwaysLoaded": false,
        "file": "assets/Armor_Bar2.png",
        "kind": "image",
        "metadata": "{\"extension\":\".png\"}",
        "name": "Armor_Bar2",
        "smoothed": false,
        "userAdded": false
      },
      {
        "alwaysLoaded": false,
        "file": "assets/NewSprite3.png",
        "kind": "image",
        "metadata": "{\"extension\":\".png\"}",
        "name": "NewSprite3",
        "smoothed": false,
        "userAdded": false
      }
    ],
    "resourceFolders": []
  },
  "objects": [],
  "objectsFolderStructure": {
    "folderName": "__ROOT"
  },
  "objectsGroups": [],
  "variables": [
    {
      "name": "Health",
      "type": "number",
      "value": 5
    }
  ],
  "layouts": [
    {
      "__REFERENCE_TO_SPLIT_OBJECT": true,
      "referenceTo": "/layouts/level1"
    },
    {
      "__REFERENCE_TO_SPLIT_OBJECT": true,
      "referenceTo": "/layouts/game-over"
    }
  ],
  "externalEvents": [],
  "eventsFunctionsExtensions": [
    {
      "__REFERENCE_TO_SPLIT_OBJECT": true,
      "referenceTo": "/eventsFunctionsExtensions/firebullet"
    },
    {
      "__REFERENCE_TO_SPLIT_OBJECT": true,
      "referenceTo": "/eventsFunctionsExtensions/panelspritecontinuousbar"
    },
    {
      "__REFERENCE_TO_SPLIT_OBJECT": true,
      "referenceTo": "/eventsFunctionsExtensions/timedbackandforthmovement"
    },
    {
      "__REFERENCE_TO_SPLIT_OBJECT": true,
      "referenceTo": "/eventsFunctionsExtensions/stayonscreen"
    },
    {
      "__REFERENCE_TO_SPLIT_OBJECT": true,
      "referenceTo": "/eventsFunctionsExtensions/smoothcamera"
    },
    {
      "__REFERENCE_TO_SPLIT_OBJECT": true,
      "referenceTo": "/eventsFunctionsExtensions/topdownmovementanimator"
    }
  ],
  "externalLayouts": [],
  "externalSourceFiles": []
}